guiabolso2csv/__init__.py
guiabolso2csv/__main__.py
guiabolso2csv/guia_bolso.py
guiabolso2csv-0.6.dist-info/LICENSE.txt
guiabolso2csv-0.6.dist-info/METADATA
guiabolso2csv-0.6.dist-info/WHEEL
guiabolso2csv-0.6.dist-info/entry_points.txt
guiabolso2csv-0.6.dist-info/top_level.txt
guiabolso2csv-0.6.dist-info/RECORD
