Metadata-Version: 2.1
Name: guiabolso2csv
Version: 0.6
Summary: GuiaBolso2csv is a simple Python program that can be used todownload GuiaBolso transactions in a csv format.
Home-page: https://github.com/hsadok/guiabolso2csv
Author: Hugo Sadok
Author-email: hugo@sadok.com.br
License: GPLv3
Download-URL: https://github.com/hsadok/guiabolso2csv/archive/0.4.tar.gz
Keywords: finance,guiabolso,excel,csv,xlsx
Platform: UNKNOWN
Classifier: Development Status :: 4 - Beta
Classifier: Intended Audience :: Developers
Classifier: License :: OSI Approved :: GNU General Public License v3 (GPLv3)
Classifier: Natural Language :: English
Classifier: Programming Language :: Python :: 2.7
Requires-Dist: requests
Requires-Dist: click
Requires-Dist: unicodecsv
Requires-Dist: openpyxl
